LICENSE
MANIFEST.in
README.md
setup.py
flask_ext_request_id/__init__.py
flask_ext_request_id/log_filter.py
flask_ext_request_id/request_id.py
flask_ext_request_id.egg-info/PKG-INFO
flask_ext_request_id.egg-info/SOURCES.txt
flask_ext_request_id.egg-info/dependency_links.txt
flask_ext_request_id.egg-info/not-zip-safe
flask_ext_request_id.egg-info/top_level.txt