Metadata-Version: 2.1
Name: flask-ext-request-id
Version: 0.0.2
Summary: flask app init request id
Home-page: https://github.com/meanstrong/flask-ext-request-id
Author: pengmingqiang
Author-email: rockypengchina@outlook.com
Maintainer: pengmingqiang
Maintainer-email: rockypengchina@outlook.com
License: GPLv3
Platform: any
